{"c(\"package:dendextend\", \"package:data.table\")":["set"],"c(\"package:generics\", \"package:base\")":["as.factor"],"c(\"package:git2r\", \"package:dplyr\")":["pull"],"c(\"package:kernlab\", \"package:flexmix\", \"package:flexclust\", \"package:arules\", \"package:stats\")":["predict"],"c(\"package:knitr\", \"package:kableExtra\")":["kable"],"c(\"package:lava\", \"package:dplyr\", \"package:ggplot2\")":["vars"],"c(\"package:OpenMx\", \"package:base\")":["nrow"],"c(\"package:randomForest\", \"package:ggplot2\")":["margin"],"c(\"package:rgeos\", \"package:base\")":["row.names"],"c(\"package:rstatix\", \"package:plotly\", \"package:MASS\", \"package:dplyr\")":["select"],"c(\"package:rstatix\", \"package:plotly\", \"package:timeSeries\", \"package:dplyr\", \"package:stats\")":["filter"],"c(\"package:rstatix\", \"package:plyr\", \"package:plotly\", \"package:ggpubr\", \"package:dplyr\")":["mutate"],"c(\"package:SparseM\", \"package:stats\")":["model.matrix"],"c(\"package:timeSeries\", \"package:stats\")":["median"],"c(\"package:timeSeries\", \"package:timeDate\", \"package:arules\", \"package:base\")":["sample"],"character(0)":["theme_custom"],"package:base":["c","data.frame","factor","gsub","is.na","library","seq","set.seed"],"package:dplyr":["bind_rows","funs","if_else","mutate_at"],"package:ggplot2":["aes","coord_flip","element_text","geom_bar","geom_boxplot","geom_density","ggplot","ggtitle","labs","scale_x_continuous","scale_x_discrete","scale_y_continuous","theme","theme_minimal","xlab","ylab"],"package:glmnet":["cv.glmnet","glmnet"],"package:gridExtra":["grid.arrange"],"package:kableExtra":["kable_styling"],"package:readr":["read_csv"],"package:stats":["lm"],"package:tibble":["add_column"],"package:utils":["write.csv"]}
