{"c(\"package:mice\", \"package:base\")":["cbind","rbind"],"c(\"package:tidyr\", \"package:mice\")":["complete"],"character(0)":["class_assess"],"package:base":["apply","as.data.frame","as.factor","c","data.frame","diag","gsub","is.na","library","names","nrow","return","set.seed","sum","table"],"package:caret":["predict.train","train","trainControl"],"package:ggplot2":["aes","ggplot","position_dodge","stat_bin"],"package:mice":["mice"],"package:purrr":["map_df"],"package:tidyr":["gather"],"package:utils":["read.csv","write.csv"]}
