{"c(\"package:dplyr\", \"package:tibble\")":["glimpse"],"c(\"package:gsubfn\", \"package:base\")":["list"],"c(\"package:igraph\", \"package:dplyr\", \"package:tibble\")":["as_data_frame"],"c(\"package:kernlab\", \"package:flexmix\", \"package:flexclust\", \"package:arules\", \"package:stats\")":["predict"],"c(\"package:Matrix\", \"package:base\")":["mean"],"c(\"package:mice\", \"package:spam\", \"package:base\")":["rbind"],"c(\"package:OpenMx\", \"package:MatrixModels\", \"package:spam\", \"package:timeSeries\", \"package:Matrix\", \"package:base\")":["print"],"c(\"package:plyr\", \"package:matrixStats\", \"package:dplyr\")":["count"],"c(\"package:rstatix\", \"package:plotly\", \"package:ggpubr\", \"package:dplyr\")":["group_by"],"c(\"package:rstatix\", \"package:plotly\", \"package:MASS\", \"package:dplyr\")":["select"],"c(\"package:rstatix\", \"package:plotly\", \"package:timeSeries\", \"package:dplyr\", \"package:stats\")":["filter"],"c(\"package:rstatix\", \"package:plyr\", \"package:plotly\", \"package:ggpubr\", \"package:dplyr\")":["mutate"],"c(\"package:rstatix\", \"package:tidyr\")":["gather"],"c(\"package:tensorflow\", \"package:mlr\", \"package:generics\", \"package:caret\")":["train"],"c(\"package:urca\", \"package:RPostgreSQL\", \"package:RMySQL\", \"package:rgdal\", \"package:quantmod\", \"package:sp\", \"package:hexbin\", \"package:flexmix\", \"package:flexclust\", \"package:stats4\", \"package:spam\", \"package:diffobj\", \"package:biclust\", \"package:arules\", \"package:Matrix\", \"package:base\")":["summary"],"package:base":["c","class","factor","gsub","ifelse","is.na","library","list.files","round","set.seed","sum"],"package:caret":["trainControl"],"package:dplyr":["case_when","funs","inner_join","n","summarize_all"],"package:ggplot2":["aes","coord_flip","geom_bar","ggplot","ylab"],"package:readr":["read_csv"],"package:stats":["chisq.test"],"package:utils":["write.csv"]}
